mcsrv/__init__.py
mcsrv/__main__.py
mcsrv/api.py
mcsrv/cli.py
mcsrv/javaexecutable.py
mcsrv/prompt.py
mcsrv/properties.py
mcsrv/server.py
mcsrv/util.py
mcsrv/commands/__init__.py
mcsrv/commands/create.py
mcsrv/commands/start.py
mcsrv/launch/__init__.py
mcsrv/launch/forge.py
mcsrv/launch/jar.py
mcsrv/launch/launch.py
mcsrv_xImAnton-1.3.0.dist-info/METADATA
mcsrv_xImAnton-1.3.0.dist-info/WHEEL
mcsrv_xImAnton-1.3.0.dist-info/entry_points.txt
mcsrv_xImAnton-1.3.0.dist-info/top_level.txt
mcsrv_xImAnton-1.3.0.dist-info/RECORD
